torch_fidelity/__init__.py
torch_fidelity/datasets.py
torch_fidelity/defaults.py
torch_fidelity/feature_extractor_base.py
torch_fidelity/feature_extractor_inceptionv3.py
torch_fidelity/fidelity.py
torch_fidelity/generative_model_base.py
torch_fidelity/generative_model_modulewrapper.py
torch_fidelity/generative_model_onnx.py
torch_fidelity/helpers.py
torch_fidelity/interpolate_compat_tensorflow.py
torch_fidelity/metric_fid.py
torch_fidelity/metric_isc.py
torch_fidelity/metric_kid.py
torch_fidelity/metric_ppl.py
torch_fidelity/metrics.py
torch_fidelity/noise.py
torch_fidelity/registry.py
torch_fidelity/sample_similarity_base.py
torch_fidelity/sample_similarity_lpips.py
torch_fidelity/utils.py
torch_fidelity/version.py
torch_fidelity-0.3.0.dist-info/LICENSE.md
torch_fidelity-0.3.0.dist-info/METADATA
torch_fidelity-0.3.0.dist-info/WHEEL
torch_fidelity-0.3.0.dist-info/entry_points.txt
torch_fidelity-0.3.0.dist-info/top_level.txt
torch_fidelity-0.3.0.dist-info/RECORD
