Metadata-Version: 2.1
Name: torch_fidelity
Version: 0.3.0
Summary: High-fidelity performance metrics for generative models in PyTorch
Home-page: https://www.github.com/toshas/torch-fidelity
Author: Anton Obukhov
License: Apache License 2.0
Keywords: reproducibility,fidelity,deep,generative,adversarial,networks,gan,inception,score,frechet,distance,kernel,perceptual,path,length,isc,fid,kid,lpips,ppl
Platform: UNKNOWN
Requires-Python: >=3.6
License-File: LICENSE.md
